email_multi_check/__init__.py
email_multi_check/email_multi_check.py
email_multi_check-1.0.7.dist-info/licenses/LICENSE
email_multi_check-1.0.7.dist-info/METADATA
email_multi_check-1.0.7.dist-info/WHEEL
email_multi_check-1.0.7.dist-info/top_level.txt
email_multi_check-1.0.7.dist-info/RECORD
