Metadata-Version: 2.4
Name: email-multi-check
Version: 1.0.7
Summary: A Python package to verify email addresses using SMTP, DNS, and web auth checks
Author-email: Alexandr Vasilchenko <r00t5st@mail.ru>
License-Expression: BSD-3-Clause
Project-URL: Homepage, https://github.com/0x7f000001/email_multi_check
Requires-Python: >=3.11.9
License-File: LICENSE
Requires-Dist: dnspython>=2.6.1
Requires-Dist: pydantic>=2.8.2
Requires-Dist: idna>=3.7
Requires-Dist: requests>=2.32.3
Dynamic: license-file
